valtools/__init__.py
valtools/forecasttools/__init__.py
valtools/forecasttools/forecasts.py
valtools/histtools/__init__.py
valtools/histtools/fred.py
valtools/histtools/historicals.py
valtools/histtools/returns.py
valtools/risktools/__init__.py
valtools/risktools/beta.py
valtools/risktools/capm.py
valtools/risktools/constants.py
valtools/risktools/sp-500-historical-annual-returns.csv
valtools/utils/__init__.py
valtools/utils/forecasting_utils.py
valtools-0.0.1.dist-info/LICENSE
valtools-0.0.1.dist-info/WHEEL
valtools-0.0.1.dist-info/METADATA
valtools-0.0.1.dist-info/RECORD
